setup.py
factual/__init__.py
factual/tests.py
factual.egg-info/PKG-INFO
factual.egg-info/SOURCES.txt
factual.egg-info/dependency_links.txt
factual.egg-info/requires.txt
factual.egg-info/top_level.txt
factual/common/__init__.py
factual/common/category_helpers.py
factual/common/exceptions.py
factual/common/requests.py
factual/common/responses.py
factual/common/session.py
factual/common/shared_filter_helpers.py
factual/common/util.py
factual/v2/__init__.py
factual/v2/filter_helpers.py
factual/v2/requests.py
factual/v2/responses.py
factual/v2/session.py
factual/v2/tables.py
factual/v3/__init__.py
factual/v3/filter_helpers.py
factual/v3/requests.py
factual/v3/responses.py
factual/v3/session.py