Metadata-Version: 1.0
Name: factual
Version: 0.1.3
Summary: Wrapper for the Factual HTTP API.
Home-page: https://github.com/casebeer/factual
Author: Christopher H. Casebeer
Author-email: UNKNOWN
License: UNKNOWN
Platform: UNKNOWN
Classifier: License :: OSI Approved :: BSD License
Classifier: Intended Audience :: Developers
